{
  "num": 110,
  "url": "https://xkcd.com/110",
  "title": "Clark Gable",
  "img": "https://imgs.xkcd.com/comics/clark_gable.jpg",
  "alt": "Frankly, my dear, I don't give a BITCH ASS SHIT FUCK DAMN",
  "year": "2006",
  "month": "6",
  "day": "2",
  "transcript": "[Famous image of Gone with the Wind with Rhett Butler (Clark Gable) kissing Scarlett O'Hara (Vivien Leigh).]\nThe line was actually supposed to be \"Frankly, my dear, I couldn't care less.\" It's just that Clark Gable had Tourette's."
}