{
  "num": 1309,
  "url": "https://xkcd.com/1309",
  "title": "Infinite Scrolling",
  "img": "https://imgs.xkcd.com/comics/infinite_scrolling.png",
  "alt": "Maybe we should give up on the whole idea of a 'back' button. 'Show me that thing I was looking at a moment ago' might just be too complicated an idea for the modern web.",
  "year": "2013",
  "month": "12",
  "day": "27",
  "transcript": "[Megan stands at a desk, reading a book, touching it very gingerly. Cueball is standing behind her.\nCueball: Why are you turning the pages like that?\nMegan: If I touch the wrong thing, I'll lose my place and have to start over.[Caption below the panel:]\nIf books worked like infinite-scrolling webpages"
}