{
  "num": 1771,
  "url": "https://xkcd.com/1771",
  "title": "It Was I",
  "img": "https://imgs.xkcd.com/comics/it_was_i.png",
  "alt": "It me, your father.",
  "year": "2016",
  "month": "12",
  "day": "12",
  "transcript": "[Emperor Palpatine, Luke Skywalker, and Darth Vader in throne room]\nEmperor: It was I who allowed the Alliance to know the location of the shield generator.\nLuke: You mean \"It was me.\" You're following an archaic grammar rule.[Zoomed in on Darth Vader, with the Emperor speaking off panel]\nEmperor: It was me who allowed the-\nVader: No, my master, an archaic tone is appropriate here. The sentence sounds-[Zoomed in on Luke Skywalker, with the Emperor speaking off panel]\nEmperor: It was I who allowed-\nLuke: Come on, the accusative case is fine. Nominative pronouns are-[Zoomed in on the Emperor, with Darth Vader responding off panel]\nEmperor: It me\nEmperor: I allowed it\nVader: My master,\nVader: Please never say that again."
}