{
  "num": 1982,
  "url": "https://xkcd.com/1982",
  "title": "Evangelism",
  "img": "https://imgs.xkcd.com/comics/evangelism.png",
  "alt": "The wars between the \"OTHER PRIMATES OPEN THEM FROM THE SMALL END\" faction versus the \"BUT THE LITTLE BIT OF BANANA AT THE SMALL END IS GROSS\" faction consumed Europe for generations.",
  "year": "2018",
  "month": "4",
  "day": "18",
  "transcript": "[A chart is shown with a line drawn from left to right with five markers on it. Each marker has a line going to it from a labeled below the main line. Above this there is a title and right below that a label above an arrow pointing to the right.]\nPeople by intensity of evangelism\nMore intenseReligious proselytizers\nPeople who want the US to switch to metric\nPeople who want the US to switch to metric but keep Fahrenheit\nPeople who threw away their socks and bought all one kind\nPeople who open bananas from the other end"
}