{
  "num": 2078,
  "url": "https://xkcd.com/2078",
  "title": "Popper",
  "img": "https://imgs.xkcd.com/comics/popper.png",
  "alt": "At least, I don't think there's evidence. My claim that there's no evidence hasn't been falsified. At least, not that I know of.",
  "year": "2018",
  "month": "11",
  "day": "28",
  "transcript": "[Miss Lenhart is teaching a class of three students; Hairy, Ponytail, and Science Girl, sitting behind their desks.]\nMiss Lenhart: There's no evidence that Karl Popper wasn't born on July 28th, 1902.\nMiss Lenhart: No one has proven that he didn't grow up in Vienna..."
}