{
  "num": 2119,
  "url": "https://xkcd.com/2119",
  "title": "Video Orientation",
  "img": "https://imgs.xkcd.com/comics/video_orientation.png",
  "alt": "CIRCULAR VIDEO - PROS: Solves aspect ratio problem. CONS: Never trust anyone who talks to you from inside a circle.",
  "year": "2019",
  "month": "3",
  "day": "4",
  "transcript": "[The image shows three columns by three rows with the following headers:]\nVideo Orientation\nPros\nCons[First row:]\n[A wide picture with a text above:]\nHorizontal\n[Pros are:]\nLooks normal to old people\nFormat used by a century of cinema\n[Cons are:]\nHumans are taller than are wide\nI'm not turning my phone sideways[Second row:]\n[A tall picture with a text above:]\nVertical\n[Pros are:]\nHow most normal people shoot and watch video now so we may as well accept it\n[Cons are:]\nHuman world is mostly a horizontal plane[Third row:]\n[A picture rotated by 45 degrees with a text above:]\nDiagonal\n[Pros are:]\nBold and dynamic\nEqually annoying to all viewers\nGood compromise\n[Cons are:]\nNone"
}