{
  "num": 2223,
  "url": "https://xkcd.com/2223",
  "title": "Screen Time",
  "img": "https://imgs.xkcd.com/comics/screen_time.png",
  "alt": "These new Bluetooth socks are great, but it's troubling to learn that I average almost 14 hours of Shoe Time a day.",
  "year": "2019",
  "month": "11",
  "day": "1",
  "transcript": "[Cueball  is looking down at his phone. The text is what he reads on the screen, as shown by a zigzag line emanating from a starburst at the top of the phone.]\nPhone: Screen time report:\nPhone: While awake, you averaged 2H 48M per day looking at things other than your phone. That's up 6% from last week![Caption below the panel]\nAt some point, it starts making more sense to track non-screen time."
}