{
  "num": 2360,
  "url": "https://xkcd.com/2360",
  "title": "Common Star Types",
  "img": "https://imgs.xkcd.com/comics/common_star_types.png",
  "alt": "This article is about Eta Carinae, a luminous blue hypergiant with anomalous Fe[ii] emission spectra. For the 1998 Brad Bird film, see The Iron Giant (film).",
  "year": "2020",
  "month": "9",
  "day": "16",
  "transcript": "Common star typesYellow dwarf\nWarm, stable, slowly-growingWhite dwarf\nSmall, hot, dimRed giant\nHuge, cool, luminousRed dwarf\nSmall, cool, ancient, dimGreen elf\nOld, diminishes into the westBlue giant\nLarge, hot, short-livedTeal sphynx\nCryptic, eternalGray wizard\nWise, powerful, mercurialIndigo banshee\nBright, portentous, extremely loudBeige gorgon\nDangerous to observe at optical wavelengths."
}