{
  "num": 2567,
  "url": "https://xkcd.com/2567",
  "title": "Language Development",
  "img": "https://imgs.xkcd.com/comics/language_development.png",
  "alt": "The worst is the Terrible Twos, when they're always throwing things and shrieking, \"forsooth, to bed thou shalt not take me, cur!\"",
  "year": "2022",
  "month": "1",
  "day": "12",
  "transcript": "[Megan and Cueball stand to the right of the frame, discussing her baby. The baby has dark hair and sits on the left side of a table in an elevated baby chair.]\nMegan: He's only 1, so he still mostly speaks proto-Indo-European.\nMegan: But we've heard a few Germanic words already, so Old English can't be far off.\nCueball: They progress so fast!\nBaby: *melg-\nBaby: *pl(e)hk-"
}