{
  "num": 2620,
  "url": "https://xkcd.com/2620",
  "title": "Health Data",
  "img": "https://imgs.xkcd.com/comics/health_data.png",
  "alt": "Donate now to help us find a cure for causality. No one should have to suffer through events because of other events.",
  "year": "2022",
  "month": "5",
  "day": "16",
  "transcript": "[Cueball and Doctor Ponytail are talking to each other. Cueball is sitting on an examination table and Doctor Ponytail, in a doctor's coat, is looking down and reading from a clipboard with some illegible writing on it.]\nDoctor Ponytail: I'm taking a look at your numbers, and it doesn't look good.\nDoctor Ponytail: You have a lot of measurements. Quite a few variables.[Same setting but Doctor Ponytail looks up at Cueball.]\nCueball: Is that... bad?\nDoctor Ponytail: Variables are the #1 risk factor for outcomes.\nDoctor Ponytail: The past is a big contributor to the future.[Same setting but Doctor Ponytail puts her arm with the clipboard down.]\nCueball: Isn't that just causality?\nDoctor Ponytail: Causality is the leading cause of death in this country.[Same setting.] \nCueball: So what are my odds?\nDoctor Ponytail: Do you have a family history?\nCueball: Of what?\nDoctor Ponytail: Just, in general.\nCueball: ...Yes?\nDoctor Ponytail: Oh no."
}