{
  "num": 631,
  "url": "https://xkcd.com/631",
  "title": "Anatomy Text",
  "img": "https://imgs.xkcd.com/comics/anatomy_text.png",
  "alt": "For many of the anatomy pictures on Wikipedia, I think this is actually not far from reality. They only look all formal and professional due to careful cropping.",
  "year": "2009",
  "month": "9",
  "day": "2",
  "transcript": "Plate 15: Female breast\n[There is a drawing of a breast, with 'breast', 'areola', and 'nipple' labeled.]Plate 16: External female genitalia\n[There is a picture of external female genitalia. 'labia majora', 'labia minora', 'clitoris', 'urethral opening', and 'vagina' are labeled.  Voice #1's speech bubble partly covers the middle of the genitalia.]\nVoice #1: HEY!Plate 17: External male genitalia\n[There is salt, ketchup, and mustard to one side.]\nVoice #2: Shit!\nVoice #1: What the hell?  You can't do that in here.\nVoice #2: Megan, get off the table!\nVoice #2: Grab the tripod!Plate 18: Erect Penis\n[The picture appears to be at an angle. Megan is running.]\nVoice #1: We're calling the cops!\nVoice #2: RUN!\nVoice #1: TGI Friday's is a family establishment!"
}