{
  "num": 711,
  "url": "https://xkcd.com/711",
  "title": "Seismograph",
  "img": "https://imgs.xkcd.com/comics/seismograph.png",
  "alt": "The reverse only works if the subject has a nervous twitch.",
  "year": "2010",
  "month": "3",
  "day": "8",
  "transcript": "[Cueball is standing over another man, who is strapped into a chair with wires attached to his head and arms. The wires lead to a large lie detector on a stand next to him, which has jagged lines drawn across it.]\nCueball: IS THERE AN EARTHQUAKE HAPPENING?!\nSitting man: No!\nLie detector: scritch scritchPro tip: In a pinch, a lie detector can double as a seismograph."
}