{
  "num": 741,
  "url": "https://xkcd.com/741",
  "title": "Blogging",
  "img": "https://imgs.xkcd.com/comics/blogging.png",
  "alt": "I'm looking to virally monetize your eyeballs by selling them for transplants.",
  "year": "2010",
  "month": "5",
  "day": "17",
  "transcript": "[Cueball stands on a stage before a large audience, holding a pointer and using it to highlight something on a screen behind him. He interacts with a member of the audience after making a point.]\nCueball: The key to making a successful blog is building a relationship with your readers.\nAudience Member: I thought it was \"make your updates good so people will want to read them.\"\nCueball: We'll discuss content generation in part three.\nAudience Member: Awesome! I LOVE content."
}