{
  "num": 868,
  "url": "https://xkcd.com/868",
  "title": "Nolan Chart",
  "img": "https://imgs.xkcd.com/comics/nolan_chart.png",
  "alt": "Also in the right quadrant are NFPA-compliant chemical manufacturers and Sir Charles Wheatstone. Sharing the top with the internet libertarians are Nate Silver and several politically-active kite designers.",
  "year": "2011",
  "month": "3",
  "day": "4",
  "transcript": "[Diamond-shaped four-panel diagram with each panel labeled. Two arrows indicate axis up along the left and right lower side of the diamond:]\n[Left]: Political opinions\n[Right]: Love of diamond-shaped diagrams\n[Top panel]: Internet libertarians\n[Left panel]: Democrats, Republicans\n[Right panel]: Baseball fans\n[Bottom panel]: Other"
}