{
  "num": 928,
  "url": "https://xkcd.com/928",
  "title": "Mimic Octopus",
  "img": "https://imgs.xkcd.com/comics/mimic_octopus.png",
  "alt": "Even if the dictionaries are starting to give in, I refuse to accept 'octopi' as a word mainly because--I'm not making this up--there's a really satisfying climactic scene in the Orson Scott Card horror novel 'Lost Boys' which hinges on it being an incorrect pluralization.",
  "year": "2011",
  "month": "7",
  "day": "22",
  "transcript": "[Captions above the panel:]\nSoutheast Asian Sea Life\nIdentification Chart\n[The chart consist of 14 black silhouettes which includes eight individual fish and several other object/animals. From top left: A fish, a fish, a tuna, a clownfish, a fish, a lionfish, a shark, a sea lilies, an angler fish, an anchor with chain, a submarine, a scuba diver, a school of seven large and four small fish, and and at the bottom right a silhouette of an octopus displaying eight arms and a tilted head with large white eyes. All 14 are labeled the same except the octopus:]\nMimic Octopus\nMimic Octopus\nMimic Octopus\nMimic Octopus\nMimic Octopus\nMimic Octopus\nMimic Octopus\nMimic Octopus\nMimic Octopus\nMimic Octopus\nMimic Octopus\nMimic Octopus\nMimic Octopus\nTwo Mimic Octopuses"
}