{
  "num": 93,
  "url": "https://xkcd.com/93",
  "title": "Jeremy Irons",
  "img": "https://imgs.xkcd.com/comics/jeremy_irons.jpg",
  "alt": "Movies that I know word-for-word, part one",
  "year": "2006",
  "month": "4",
  "day": "24",
  "transcript": "[Cueball points at Megan with his mouth open. Jeremy Irons stands behind him.]\nJeremy Irons: But as THICK as you are, pay attention\nJeremy Irons: My words are a matter of PRIDE!My goal: To make enough money to hire Jeremy Irons, the voice of Scar from The Lion King, to follow me around and do my dialogue."
}